Nightanday_first_package/__init__.py
Nightanday_first_package/cli.py
Nigtanday_first_package-1.0.dist-info/METADATA
Nigtanday_first_package-1.0.dist-info/WHEEL
Nigtanday_first_package-1.0.dist-info/entry_points.txt
Nigtanday_first_package-1.0.dist-info/top_level.txt
Nigtanday_first_package-1.0.dist-info/RECORD
