Metadata-Version: 2.2
Name: Nigtanday_first_package
Version: 1.0
Summary: A simple CLI package but an amazing one.
Requires-Dist: click==8.1.3
